coj_judger/__init__.py
coj_judger/api.py
coj_judger/constants.py
coj_judger/entity.py
coj_judger/interface.py
coj_judger/judger.py
coj_judger/server.py
coj_judger/utils.py
coj_judger-0.17.dist-info/METADATA
coj_judger-0.17.dist-info/WHEEL
coj_judger-0.17.dist-info/top_level.txt
coj_judger-0.17.dist-info/RECORD
