Metadata-Version: 2.1
Name: coj_judger
Version: 0.17
Summary: A Framework for developing a judger of COJ.
Home-page: https://github.com/CZOI-Project/JudgerFramework
Author: Caiwen
Author-email: 3102733279@qq.com
